iterable_data_import/__init__.py
iterable_data_import/data_sources/__init__.py
iterable_data_import/data_sources/data_source.py
iterable_data_import/data_sources/file_system.py
iterable_data_import/error_recorders/__init__.py
iterable_data_import/error_recorders/api_error_recorder.py
iterable_data_import/error_recorders/map_error_recorder.py
iterable_data_import/errors.py
iterable_data_import/import_action.py
iterable_data_import/importers/__init__.py
iterable_data_import/importers/importer.py
iterable_data_import/importers/iterable_request.py
iterable_data_import/importers/no_op_importer.py
iterable_data_import/importers/sync_api_client.py
iterable_data_import/importers/sync_api_importer.py
iterable_data_import/iterable_data_import.py
iterable_data_import/iterable_resource.py
iterable_data_import-0.1.0.dist-info/LICENSE
iterable_data_import-0.1.0.dist-info/WHEEL
iterable_data_import-0.1.0.dist-info/METADATA
iterable_data_import-0.1.0.dist-info/RECORD
