Metadata-Version: 2.1
Name: iterable-data-import
Version: 0.1.0
Summary: A library for ad-hoc bulk imports to Iterable
License: MIT
Author: julianmclain
Author-email: julianrmclain@gmail.com
Requires-Python: >=3.7,<4.0
Classifier: License :: OSI Approved :: MIT License
Classifier: Programming Language :: Python :: 3
Classifier: Programming Language :: Python :: 3.7
Classifier: Programming Language :: Python :: 3.8
Classifier: Programming Language :: Python :: 3.9
Requires-Dist: requests (>=2.26.0,<3.0.0)
